{"GlobalPropertiesHash":"4HLATZcf6C9zMygVdh5TjBkzzsgq4D5zQT4rEMB//w0=","FingerprintPatternsHash":"gq3WsqcKBUGTSNle7RKKyXRIwh7M8ccEqOqYvIzoM04=","PropertyOverridesHash":"8ZRc1sGeVrPBx4lD717BgRaQekyh78QKV9SKsdt638U=","InputHashes":["N9aM4bqlGs0e6Kr7yRoB7r2qQVRkJuej3Gt283ISwUI=","pSTIwW1dn\u002Bk6ujA65rwHgUTnKPUQUW4Q3FYAduM2Sdk=","sYEhhzwxlSKjcdChCN9YQgf2uAi0lknqqSgt4UdypnA=","nM8NdAQuFe477tHc0PPrZJCCyw4c2hxnYxG0V1dFHUo="],"CachedAssets":{"N9aM4bqlGs0e6Kr7yRoB7r2qQVRkJuej3Gt283ISwUI=":{"Identity":"D:\\Projects\\Blazor\\Entertainment-Tracker\\Entertainment_Tracker.Client\\wwwroot\\appsettings.Development.json","SourceId":"Entertainment_Tracker.Client","SourceType":"Discovered","ContentRoot":"D:\\Projects\\Blazor\\Entertainment-Tracker\\Entertainment_Tracker.Client\\wwwroot\\","BasePath":"/","RelativePath":"appsettings.Development#[.{fingerprint}]?.json","AssetKind":"All","AssetMode":"All","AssetRole":"Primary","AssetMergeBehavior":null,"AssetMergeSource":"","RelatedAsset":null,"AssetTraitName":null,"AssetTraitValue":null,"Fingerprint":"tswichycbp","Integrity":"c/lfngzrIF/BxNxQwHaX/Pop1wh4aMKu8dUEyzjHcew=","CopyToOutputDirectory":"Never","CopyToPublishDirectory":"PreserveNewest","OriginalItemSpec":"wwwroot\\appsettings.Development.json","FileLength":127,"LastWriteTime":"2026-03-03T01:37:26.9810922+00:00"},"pSTIwW1dn\u002Bk6ujA65rwHgUTnKPUQUW4Q3FYAduM2Sdk=":{"Identity":"D:\\Projects\\Blazor\\Entertainment-Tracker\\Entertainment_Tracker.Client\\wwwroot\\appsettings.json","SourceId":"Entertainment_Tracker.Client","SourceType":"Discovered","ContentRoot":"D:\\Projects\\Blazor\\Entertainment-Tracker\\Entertainment_Tracker.Client\\wwwroot\\","BasePath":"/","RelativePath":"appsettings#[.{fingerprint}]?.json","AssetKind":"All","AssetMode":"All","AssetRole":"Primary","AssetMergeBehavior":null,"AssetMergeSource":"","RelatedAsset":null,"AssetTraitName":null,"AssetTraitValue":null,"Fingerprint":"tswichycbp","Integrity":"c/lfngzrIF/BxNxQwHaX/Pop1wh4aMKu8dUEyzjHcew=","CopyToOutputDirectory":"Never","CopyToPublishDirectory":"PreserveNewest","OriginalItemSpec":"wwwroot\\appsettings.json","FileLength":127,"LastWriteTime":"2026-03-03T01:37:27.0193198+00:00"}},"CachedCopyCandidates":{}}